biab.cpython-39-darwin.so
biab_library-0.4.1.dist-info/LICENSE
biab_library-0.4.1.dist-info/METADATA
biab_library-0.4.1.dist-info/WHEEL
biab_library-0.4.1.dist-info/top_level.txt
biab_library-0.4.1.dist-info/RECORD
