Metadata-Version: 2.1
Name: biab-library
Version: 0.4.1
Summary: A converter for band-in-a-box files
Home-page: https://github.com/andreamust/biab
Author: Andrea Poltronieri
Author-email: andrea.poltronieri21@gmail.com
Requires-Python: >=3.6
License-File: LICENSE
Provides-Extra: test
Requires-Dist: pytest ; extra == 'test'
